setup.py
shinkenplugins/__init__.py
shinkenplugins.plugins.linux_bandwidth.egg-info/PKG-INFO
shinkenplugins.plugins.linux_bandwidth.egg-info/SOURCES.txt
shinkenplugins.plugins.linux_bandwidth.egg-info/dependency_links.txt
shinkenplugins.plugins.linux_bandwidth.egg-info/entry_points.txt
shinkenplugins.plugins.linux_bandwidth.egg-info/namespace_packages.txt
shinkenplugins.plugins.linux_bandwidth.egg-info/requires.txt
shinkenplugins.plugins.linux_bandwidth.egg-info/top_level.txt
shinkenplugins/plugins/__init__.py
shinkenplugins/plugins/linux_bandwidth/__init__.py
shinkenplugins/plugins/linux_bandwidth/linux_bandwidth.py