Metadata-Version: 1.0
Name: shinkenplugins.plugins.linux-bandwidth
Version: 1.2
Summary: Check Linux bandwidth usage per month
Home-page: https://github.com/savoirfairelinux/sfl-shinken-plugins
Author: Grégory Starck
Author-email: gregory.starck@savoirfairelinux.com
License: GPL3+
Platform: any
